monochromist/__init__.py
monochromist/math_version/__init__.py
monochromist/math_version/classes.py
monochromist/math_version/clean.py
monochromist/math_version/postprocess.py
monochromist/math_version/process.py
monochromist/opencv_version/__init__.py
monochromist/opencv_version/classes.py
monochromist/opencv_version/find_mask.py
monochromist/opencv_version/post_editing.py
monochromist/opencv_version/process.py
monochromist-1.0.3.dist-info/entry_points.txt
monochromist-1.0.3.dist-info/LICENSE
monochromist-1.0.3.dist-info/WHEEL
monochromist-1.0.3.dist-info/METADATA
monochromist-1.0.3.dist-info/RECORD
