Metadata-Version: 2.1
Name: monochromist
Version: 1.0.3
Summary: Convert your sketch into contour with transparent background
Home-page: https://github.com/ozzzzz/monochromist
License: MIT
Author: Bogdan Neterebskii
Author-email: bog2dan1@gmail.com
Requires-Python: >=3.8,<4.0
Classifier: License :: OSI Approved :: MIT License
Classifier: Programming Language :: Python :: 3
Classifier: Programming Language :: Python :: 3.8
Classifier: Programming Language :: Python :: 3.9
Requires-Dist: Pillow (>=8.2.0,<9.0.0)
Requires-Dist: click (>=7.1.2,<8.0.0)
Requires-Dist: colour (>=0.1.5,<0.2.0)
Requires-Dist: loguru (>=0.5.3,<0.6.0)
Requires-Dist: numpy (>=1.20.2,<2.0.0)
Requires-Dist: opencv-python (>=4.5.1,<5.0.0)
Project-URL: Repository, https://github.com/ozzzzz/monochromist
